sniped/__init__.py
sniped/__main__.py
sniped/compile_languages.py
sniped/configs.py
sniped/languages.py
sniped/services.py
sniped/themes.py
sniped-1.2.0.dist-info/entry_points.txt
sniped-1.2.0.dist-info/WHEEL
sniped-1.2.0.dist-info/METADATA
sniped-1.2.0.dist-info/RECORD
