Metadata-Version: 2.1
Name: sniped
Version: 1.2.0
Summary: Turn snippets of code into beautiful images.
Author: Rodrigo Girão Serrão
Author-email: 5621605+RodrigoGiraoSerrao@users.noreply.github.com
Requires-Python: >=3.9,<4.0
Classifier: Programming Language :: Python :: 3
Classifier: Programming Language :: Python :: 3.10
Classifier: Programming Language :: Python :: 3.9
Requires-Dist: rich (>=12.0.0,<13.0.0)
Requires-Dist: typer[all] (>=0.4.0,<0.5.0)
